worldofgames/CurrencyRoulette.py
worldofgames/GuessGame.py
worldofgames/Live.py
worldofgames/MainGame.py
worldofgames/ManegeGame.py
worldofgames/MemoryGame.py
worldofgames/UserAccount.py
worldofgames/__init__.py
worldofgames/account_db.json
worldofgames/main.py
WorldOfGame_pkg_guysaar8-1.0.0.dist-info/LICENSE
WorldOfGame_pkg_guysaar8-1.0.0.dist-info/METADATA
WorldOfGame_pkg_guysaar8-1.0.0.dist-info/WHEEL
WorldOfGame_pkg_guysaar8-1.0.0.dist-info/entry_points.txt
WorldOfGame_pkg_guysaar8-1.0.0.dist-info/top_level.txt
WorldOfGame_pkg_guysaar8-1.0.0.dist-info/RECORD
