Metadata-Version: 2.1
Name: WorldOfGame-pkg-guysaar8
Version: 1.0.0
Summary: Python Games package
Home-page: UNKNOWN
Author: Guy Saar
License: MIT
Platform: UNKNOWN
Classifier: License :: OSI Approved :: MIT License
Classifier: Programming Language :: Python :: 3
Classifier: Programming Language :: Python :: 3.6
Requires-Dist: requests
